<?xml version='1.0' encoding='UTF-8'?>
<spesifisertSummertSkattegrunnlag xmlns="urn:no:skatteetaten:datasamarbeid:spesifisertsummertskattegrunnlag:v1">
  <personidentifikator>12345678910</personidentifikator>
  <inntektsaar>2016</inntektsaar>
  <grunnlag>
    <tekniskNavn>samletPensjonFraEOeSStatSomTilsvarerNorskAlderspensjonEllerAvtalefestetPensjon</tekniskNavn>
    <beloep>489730</beloep>
    <kategori>inntekt</kategori>
  </grunnlag>
  <grunnlag>
    <tekniskNavn>samletAnnenTrekkpliktigPensjon</tekniskNavn>
    <beloep>859460</beloep>
    <kategori>inntekt</kategori>
  </grunnlag>
  <grunnlag>
    <tekniskNavn>samletTrekkpliktigUtgiftsgodtgjoerelse</tekniskNavn>
    <beloep>29730</beloep>
    <kategori>inntekt</kategori>
  </grunnlag>
  <grunnlag>
    <tekniskNavn>samletUfoeretrygdFraFolketrygden</tekniskNavn>
    <beloep>609460</beloep>
    <kategori>inntekt</kategori>
  </grunnlag>
  <grunnlag>
    <tekniskNavn>samletSkattepliktigOverskuddFraUtleieAvFastEiendom</tekniskNavn>
    <beloep>279730</beloep>
    <kategori>inntekt</kategori>
  </grunnlag>
  <grunnlag>
    <tekniskNavn>samletPersoninntektFraEnkeltpersonforetakInnenFamiliebarnehageEllerDagmammaIEgetHjem</tekniskNavn>
    <beloep>229730</beloep>
    <kategori>inntekt</kategori>
  </grunnlag>
  <grunnlag>
    <tekniskNavn>samletOverskuddPaaUtgiftsgodtgjoerelse</tekniskNavn>
    <beloep>569460</beloep>
    <kategori>inntekt</kategori>
  </grunnlag>
  <grunnlag>
    <tekniskNavn>samletAlderspensjonFraFolketrygden</tekniskNavn>
    <beloep>139730</beloep>
    <kategori>inntekt</kategori>
  </grunnlag>
  <grunnlag>
    <tekniskNavn>samletUnderskuddINaeringsvirksomhet</tekniskNavn>
    <beloep>529460</beloep>
    <kategori>inntektsfradrag</kategori>
  </grunnlag>
  <grunnlag>
    <tekniskNavn>samletAnnenPensjonMedTrekkfritak</tekniskNavn>
    <beloep>599460</beloep>
    <kategori>inntekt</kategori>
  </grunnlag>
  <grunnlag>
    <tekniskNavn>samletPersoninntektFraEnkeltpersonforetakInnenJordbrukReindriftSkiferproduksjonOgAnnenNaering</tekniskNavn>
    <beloep>1099460</beloep>
    <kategori>inntekt</kategori>
  </grunnlag>
  <grunnlag>
    <tekniskNavn>samletTrekkpliktigLoennsinntektUtenTrydgeavgiftsplikt</tekniskNavn>
    <beloep>289730</beloep>
    <kategori>inntekt</kategori>
  </grunnlag>
  <grunnlag>
    <tekniskNavn>samletLoennsinntektKunMedTrygdeavgiftsplikt</tekniskNavn>
    <beloep>539730</beloep>
    <kategori>inntekt</kategori>
  </grunnlag>
  <grunnlag>
    <tekniskNavn>samletOverskuddAvDeltakerlignetSelskapInnenFiskeEllerFamiliebarnehage</tekniskNavn>
    <beloep>429730</beloep>
    <kategori>inntekt</kategori>
  </grunnlag>
  <grunnlag>
    <tekniskNavn>samletOvergangsstoenadTilEnsligOgEtterlatt</tekniskNavn>
    <beloep>399730</beloep>
    <kategori>inntekt</kategori>
  </grunnlag>
  <grunnlag>
    <tekniskNavn>samletBarnepensjonOgLivrente</tekniskNavn>
    <beloep>189460</beloep>
    <kategori>inntekt</kategori>
  </grunnlag>
  <grunnlag>
    <tekniskNavn>samletSkattepliktigOverskuddFraUtleieAvFastEiendomIUtlandet</tekniskNavn>
    <beloep>59730</beloep>
    <kategori>inntekt</kategori>
  </grunnlag>
  <grunnlag>
    <tekniskNavn>samletInntektSomGirRettTilSaerskiltFradragForSjoefolk</tekniskNavn>
    <beloep>509730</beloep>
    <kategori>inntekt</kategori>
  </grunnlag>
  <grunnlag>
    <tekniskNavn>samletRenteinntektPaaLaanTilSelskapSomSkalEkstrabeskattes</tekniskNavn>
    <beloep>89730</beloep>
    <kategori>inntekt</kategori>
  </grunnlag>
  <grunnlag>
    <tekniskNavn>samletPersoninntektFraEnkeltpersonforetakInnenFiskeOgFangst</tekniskNavn>
    <beloep>159730</beloep>
    <kategori>inntekt</kategori>
  </grunnlag>
  <grunnlag>
    <tekniskNavn>samletAnnenRenteinntekt</tekniskNavn>
    <beloep>579730</beloep>
    <kategori>inntekt</kategori>
  </grunnlag>
  <grunnlag>
    <tekniskNavn>samletAnnenInntekt</tekniskNavn>
    <beloep>629460</beloep>
    <kategori>inntekt</kategori>
  </grunnlag>
  <grunnlag>
    <tekniskNavn>samletSkattefriPensjonFraUtlandet</tekniskNavn>
    <beloep>339730</beloep>
    <kategori>inntekt</kategori>
  </grunnlag>
  <grunnlag>
    <tekniskNavn>samletLoennsinntekt</tekniskNavn>
    <beloep>2448380</beloep>
    <kategori>inntekt</kategori>
  </grunnlag>
  <grunnlag>
    <tekniskNavn>samletOverskuddAvEnkeltpersonforetakInnenFamiliebarnehageEllerDagmammaIEgetHjem</tekniskNavn>
    <beloep>389730</beloep>
    <kategori>inntekt</kategori>
  </grunnlag>
  <grunnlag>
    <tekniskNavn>samletOverskuddAvEnkeltpersonforetakInnenAnnenNaering</tekniskNavn>
    <beloep>759460</beloep>
    <kategori>inntekt</kategori>
  </grunnlag>
  <grunnlag>
    <tekniskNavn>samletFremfoerbartUnderskuddFraTidligereAar</tekniskNavn>
    <beloep>609460</beloep>
    <kategori>inntektsfradrag</kategori>
  </grunnlag>
  <grunnlag>
    <tekniskNavn>samletSkattepliktigUtbyttePaaAksjerRegistrertIVerdipapirsentralen</tekniskNavn>
    <beloep>129730</beloep>
    <kategori>inntekt</kategori>
  </grunnlag>
  <skjermet>false</skjermet>
  <skjoennsfastsatt>false</skjoennsfastsatt>
</spesifisertSummertSkattegrunnlag>